testax/__init__.py
testax-0.2.0.dist-info/METADATA
testax-0.2.0.dist-info/WHEEL
testax-0.2.0.dist-info/top_level.txt
testax-0.2.0.dist-info/RECORD
