Metadata-Version: 2.1
Name: testax
Version: 0.2.0
Summary: Jit-able runtime assertions for jax in numpy style.
Requires-Dist: jax
